LICENSE
pyella/__init__.py
pyella/either.py
pyella/maybe.py
pyella/py.typed
pyella/shared.py
pyella-3.1.0.dist-info/LICENSE
pyella-3.1.0.dist-info/METADATA
pyella-3.1.0.dist-info/WHEEL
pyella-3.1.0.dist-info/RECORD
