Metadata-Version: 2.1
Name: pyella
Version: 3.1.0
Summary: This library brings common monads such as `Maybe` and `Either` to your Python projects
Home-page: https://pyella.readthedocs.io
License: MPL-2.0
Keywords: monad,fp,maybe,either
Author: Ely Deckers
Maintainer: Ely Deckers
Requires-Python: >=3.8
Classifier: Intended Audience :: Developers
Classifier: License :: OSI Approved
Classifier: License :: OSI Approved :: Mozilla Public License 2.0 (MPL 2.0)
Classifier: Programming Language :: Python :: 3
Classifier: Programming Language :: Python :: 3.8
Classifier: Programming Language :: Python :: 3.9
Classifier: Programming Language :: Python :: 3.10
Classifier: Programming Language :: Python :: 3.11
Classifier: Programming Language :: Python :: 3.12
Classifier: Programming Language :: Python :: 3.13
Classifier: Topic :: Software Development :: Libraries :: Python Modules
Project-URL: Documentation, https://github.com/edeckers/pyella
Project-URL: Repository, https://github.com/edeckers/pyella.git
